quagmire/__init__.py
quagmire/_fortran.cpython-37m-darwin.so
quagmire/documentation.py
quagmire/Examples/Notebooks/Tutorial/Ex1-Creating-Meshes.ipynb
quagmire/Examples/Notebooks/Tutorial/Ex1a-QuagmireMeshVariables.ipynb
quagmire/Examples/Notebooks/Tutorial/Ex1b-QuagmireLazyFunctions.ipynb
quagmire/Examples/Notebooks/Tutorial/Ex2-Topography-Meshes.ipynb
quagmire/Examples/Notebooks/Tutorial/Ex3-Surface-Process-Meshes.ipynb
quagmire/Examples/Notebooks/Tutorial/Ex4-Multiple-downhill-pathways.ipynb
quagmire/Examples/Notebooks/Tutorial/Ex5-PreprocessingSurfaces.ipynb
quagmire/Examples/Notebooks/Tutorial/Ex6-Catchment-Analysis.ipynb
quagmire/Examples/Notebooks/WorkedExamples/WEx1-ETOPO1-workflow.ipynb
quagmire/Examples/Notebooks/WorkedExamples/WEx2-ETOPO1-Tasmania.ipynb
quagmire/_fortran.cpython-37m-darwin.so.dSYM/Contents/Info.plist
quagmire/_fortran.cpython-37m-darwin.so.dSYM/Contents/Resources/DWARF/_fortran.cpython-37m-darwin.so
quagmire/function/__init__.py
quagmire/function/function_classes.py
quagmire/function/math.py
quagmire/function/misc.py
quagmire/mesh/__init__.py
quagmire/mesh/basemesh.py
quagmire/mesh/commonmesh.py
quagmire/mesh/pixmesh.py
quagmire/mesh/trimesh.py
quagmire/surfmesh/__init__.py
quagmire/surfmesh/surfmesh.py
quagmire/tools/__init__.py
quagmire/tools/generate_xdmf.py
quagmire/tools/meshtools.py
quagmire/topomesh/__init__.py
quagmire/topomesh/topomesh.py
quagmire-0.5.0.dist-info/COPYING
quagmire-0.5.0.dist-info/COPYING.LESSER
quagmire-0.5.0.dist-info/LICENCE
quagmire-0.5.0.dist-info/METADATA
quagmire-0.5.0.dist-info/WHEEL
quagmire-0.5.0.dist-info/top_level.txt
quagmire-0.5.0.dist-info/RECORD
