Metadata-Version: 2.1
Name: quagmire
Version: 0.5.0
Summary: Python surface process framework on highly scalable unstructured meshes
Home-page: https://github.com/University-of-Melbourne-Geodynamics/quagmire
Author: Louis Moresi
Author-email: louis.moresi@unimelb.edu.au
License: UNKNOWN
Platform: UNKNOWN
Classifier: Programming Language :: Python :: 2
Classifier: Programming Language :: Python :: 2.6
Classifier: Programming Language :: Python :: 2.7
Classifier: Programming Language :: Python :: 3
Classifier: Programming Language :: Python :: 3.3
Classifier: Programming Language :: Python :: 3.4
Classifier: Programming Language :: Python :: 3.5
Classifier: Programming Language :: Python :: 3.6
Requires-Dist: numpy
Requires-Dist: stripy
